{
    "script": {
        "type": "",
        "content": ""
    },
    "specJson": {
        "category": "regression",
        "func": "brightics.function.regression$penalized_linear_regression_train",
        "name": "brightics.function.regression$penalized_linear_regression_train",
        "context": "python",
        "label": "Penalized Linear Regression Train",
        "description": "This model solves a regression model where the loss function is the linear least squares function and regularization is given. \n\n1. Ridge model solves a regression model where the loss function is the linear least squares function and regularization is given by the L2-norm. \n\n2. Lasso is a linear model trained with L1 prior as regularizer. \n\n3. ElasticNet is a linear regression with combined L1 and L2 priors as regularizer. Technically the Lasso model is optimizing the same objective function as the ElasticNet without L2 penalty.",
        "tags": [],
        "version": "3.6",
        "inputs": {
            "table": ""
        },
        "outputs": {
            "model": ""
        },
        "meta": {
            "table": {
                "type": "table"
            },
            "model": {
                "type": "model"
            }
        },
        "params": [
            {
                "id": "feature_cols",
                "label": "Feature Columns",
                "description": "",
                "mandatory": true,
                "items": [],
                "visibleOption": [],
                "control": "ColumnSelector",
                "columnType": [
                    "Integer",
                    "Long",
                    "Float",
                    "Double",
                    "Double[]"
                ],
                "validation": [],
                "multiple": true,
                "rowCount": 5
            },
            {
                "id": "label_col",
                "label": "Label Column",
                "description": "",
                "mandatory": true,
                "items": [],
                "visibleOption": [],
                "control": "ColumnSelector",
                "columnType": [
                    "Integer",
                    "Long",
                    "Float",
                    "Double"
                ],
                "validation": [],
                "multiple": false
            },
            {
                "id": "regression_type",
                "label": "Regression Type",
                "description": "Choose among 'Ridge', 'Lasso', and 'ElasticNet'.",
                "mandatory": false,
                "items": [
                    {
                        "label": "Ridge",
                        "value": "ridge",
                        "default": true
                    },
                    {
                        "label": "Lasso",
                        "value": "lasso",
                        "default": false
                    },
                    {
                        "label": "ElasticNet",
                        "value": "elastic_net",
                        "default": false
                    }
                ],
                "visibleOption": [],
                "control": "RadioButton",
                "columnType": [],
                "validation": []
            },
            {
                "id": "alpha",
                "label": "Regularization (Penalty Weight)",
                "description": "Constant that multiplies the penalty terms.",
                "mandatory": false,
                "items": [],
                "visibleOption": [],
                "control": "InputBox",
                "columnType": [],
                "validation": [],
                "placeHolder": "1.0 (value >= 0.0)",
                "type": "Double",
                "min": 0.0
            },
            {
                "id": "l1_ratio",
                "label": "L1 Ratio",
                "description": "The ElasticNet mixing parameter, with 0 <= 'L1 ratio' <= 1. For 'L1 ratio' = 0, the penalty is an L2 penalty. For 'L1 ratio' = 1, it is an L1 penalty. For 0 < 'L1 ratio' < 1, the penalty is a combination of L1 and L2.",
                "mandatory": false,
                "items": [],
                "visibleOption": [
                    {
                        "id": "regression_type",
                        "value": "elastic_net"
                    }
                ],
                "control": "InputBox",
                "columnType": [],
                "validation": [],
                "placeHolder": "0.5 (0.0 <= value <= 1.0)",
                "type": "Double",
                "min": 0.0,
                "max": 1.0
            },
            {
                "id": "fit_intercept",
                "label": "Fit Intercept",
                "description": "Whether the intercept should be estimated or not. If False, the data is assumed to be already centered.",
                "mandatory": false,
                "items": [],
                "visibleOption": [],
                "control": "BooleanRadio",
                "columnType": [],
                "validation": [],
                "defaultValue": true
            },
            {
                "id": "max_iter",
                "label": "Iterations",
                "description": "The maximum number of iterations.",
                "mandatory": false,
                "items": [],
                "visibleOption": [],
                "control": "InputBox",
                "columnType": [],
                "validation": [],
                "placeHolder": "1000 (value >= 1)",
                "type": "Integer",
                "min": 1
            },
            {
                "id": "tol",
                "label": "Tolerance",
                "description": "The tolerance for the optimization: if the updates are smaller than tolerance, the optimization code checks the dual gap for optimality and continues until it is smaller than tolerance.",
                "mandatory": false,
                "items": [],
                "visibleOption": [],
                "control": "InputBox",
                "columnType": [],
                "validation": [],
                "placeHolder": "0.0001 (value > 0.0)",
                "type": "Double"
            },
            {
                "id": "random_state",
                "label": "Seed",
                "description": "The seed of the pseudo random number generator that selects a random feature to update (default=None).",
                "mandatory": false,
                "items": [],
                "visibleOption": [],
                "control": "InputBox",
                "columnType": [],
                "validation": [],
                "type": "Integer",
                "placeHolder": ""
            },
            {
                "id": "group_by",
                "label": "Group By",
                "description": "",
                "mandatory": false,
                "items": [],
                "visibleOption": [],
                "control": "ColumnSelector",
                "columnType": [],
                "validation": [],
                "multiple": true
            }
        ]
    },
    "md": ""
}
