{
    "script": {
        "type": "",
        "content": ""
    },
    "specJson": {
        "category": "io",
        "func": "brightics.function.io$image_load",
        "name": "brightics.function.io$image_load",
        "context": "python",
        "label": "Image Load",
        "description": "Load image files.",
        "tags": [],
        "version": "3.6",
        "outputs": {
            "out_table": ""
        },
        "meta": {
            "out_table": {
                "type": "table"
            }
        },
        "params": [
            {
                "id": "path",
                "label": "Input Path",
                "description": "Directory where the image files exists.",
                "mandatory": true,
                "items": [],
                "visibleOption": [],
                "control": "InputBox",
                "columnType": [],
                "validation": [],
                "type": "String"
            },
            {
                "id": "labeling",
                "label": "Labeling",
                "description": "Method to add label to image values.",
                "mandatory": false,
                "items": [
                    {
                        "label": "Directory",
                        "value": "dir",
                        "description": "Assume the image files are saved as (Input Path)/(Label)/(Image Files).",
                        "default": true
                    },
                    {
                        "label": "None",
                        "value": "none",
                        "description": "Assume the image files are saved as (Input Path)/(Image Files). Label values are not added.",
                        "default": false
                    }
                ],
                "visibleOption": [],
                "control": "RadioButton",
                "columnType": [],
                "validation": []
            },
            {
                "id": "image_col",
                "label": "Image Column Name",
                "description": "Column name for image values.",
                "mandatory": false,
                "items": [],
                "visibleOption": [],
                "control": "InputBox",
                "columnType": [],
                "validation": [],
                "placeHolder": "image",
                "type": "String"
            }
        ]
    },
    "md": ""
}