{
  "_description": "Stop if metric does not decrease within given max steps.",
  "_label": "Stop If No Decrease",
  "params": {
    "metric_name": {
      "_label": "Metric Name",
      "_description": "Metric to track. \"loss\", \"accuracy\", etc.",
      "_value": "",
      "_optional": false,
      "_control": "input",
      "_type": "string",
      "_advancedOption": false
    },
    "max_steps_without_decrease": {
      "_label": "Max Steps Without Decrease",
      "_description": "Maximum number of training steps with no decrease in the given metric.",
      "_value": 1000,
      "_optional": false,
      "_control": "input",
      "_type": "number",
      "_advancedOption": false
    },
    "min_steps": {
      "_label": "Minimum Steps",
      "_description": "Stop is never requested if global step is less than this value.",
      "_value": 0,
      "_optional": true,
      "_control": "input",
      "_type": "number",
      "_advancedOption": false
    },
    "run_every_secs": {
      "_label": "Run Every Secs",
      "_description": "Time interval (sec) for calling stop request.",
      "_value": 60,
      "_optional": true,
      "_control": "input",
      "_type": "number",
      "_advancedOption": false
    }
  },
  "_tags": [
    "image",
    "classification",
    "early stopping"
  ],
  "_deprecated": false,
  "module": "brightics.deeplearning.runner.early_stopping",
  "name": "stop_if_no_decrease_hook",
  "updateVersion": "3.6"
}
